datacmp/__init__.py
datacmp/column_cleaning.py
datacmp/data_cleaning.py
datacmp/detailed_info.py
datacmp/run_pipeline.py
datacmp-2.0.0.dist-info/licenses/LICENSE
datacmp-2.0.0.dist-info/METADATA
datacmp-2.0.0.dist-info/WHEEL
datacmp-2.0.0.dist-info/top_level.txt
datacmp-2.0.0.dist-info/RECORD
