Metadata-Version: 2.4
Name: datacmp
Version: 2.0.0
Summary: A powerful and configurable library for exploratory data analysis (EDA) and data cleaning for machine learning workflows.
Home-page: https://github.com/MoustafaMohamed01/datacmp
Author: Moustafa Mohamed
Author-email: moustafa.mh.mohamed@gmail.com
Classifier: Programming Language :: Python :: 3
Classifier: License :: OSI Approved :: MIT License
Classifier: Operating System :: OS Independent
Requires-Python: >=3.7
License-File: LICENSE
Requires-Dist: pandas>=1.0.0
Requires-Dist: tabulate>=0.8.0
Requires-Dist: PyYAML>=6.0
Dynamic: author
Dynamic: author-email
Dynamic: classifier
Dynamic: description
Dynamic: description-content-type
Dynamic: home-page
Dynamic: license-file
Dynamic: requires-dist
Dynamic: requires-python
Dynamic: summary
